corrGraph/__init__.py
corrGraph/corrGraph.py
corrGraph-0.1.0.dist-info/LICENSE
corrGraph-0.1.0.dist-info/METADATA
corrGraph-0.1.0.dist-info/WHEEL
corrGraph-0.1.0.dist-info/top_level.txt
corrGraph-0.1.0.dist-info/RECORD
