Metadata-Version: 2.1
Name: corrGraph
Version: 0.1.0
Summary: A python module built using graph theory to analyse how attributes/features in a dataset correlate with each other
Home-page: https://github.com/mawuliadjei/corrGraph
Author: Mawuli Adjei
Author-email: mawuliadjei@gmail.com
License: UNKNOWN
Platform: UNKNOWN
Classifier: Programming Language :: Python :: 3
Classifier: License :: OSI Approved :: MIT License
Classifier: Operating System :: OS Independent
Requires-Python: >=3.8
License-File: LICENSE
Requires-Dist: nbformat==5.10.4
Requires-Dist: networkx==3.2.1
Requires-Dist: numpy==2.0.2
Requires-Dist: pandas==2.2.3
Requires-Dist: plotly==5.24.1
Requires-Dist: pyvis==0.3.2
Requires-Dist: scikit-learn==1.5.2
Requires-Dist: seaborn==0.13.2
Requires-Dist: Sphinx==7.4.7
Requires-Dist: sphinx-rtd-theme==3.0.1
